grepctl/__init__.py
grepctl/cli.py
grepctl/config.py
grepctl/enable_services.py
grepctl/grepctl.py
grepctl/health_check.py
grepctl/ml_generate_setup.py
grepctl/search_api.py
grepctl/api/__init__.py
grepctl/api/server.py
grepctl/api/theme.py
grepctl/bigquery/__init__.py
grepctl/bigquery/connection.py
grepctl/bigquery/queries.py
grepctl/bigquery/queries_ml.py
grepctl/bigquery/schema.py
grepctl/ingestion/__init__.py
grepctl/ingestion/audio_processor.py
grepctl/ingestion/base.py
grepctl/ingestion/chunking.py
grepctl/ingestion/embeddings.py
grepctl/ingestion/image_processor.py
grepctl/ingestion/pdf_processor.py
grepctl/ingestion/text_extractor.py
grepctl/ingestion/video_processor.py
grepctl/scripts/complete_vision_analysis.py
grepctl/scripts/extract_all_pdfs_hybrid.py
grepctl/scripts/extract_pdfs_with_docai.py
grepctl/scripts/fix_embeddings.py
grepctl/scripts/generate_embeddings.py
grepctl/scripts/ingest_audio_files.py
grepctl/scripts/ingest_json_csv_fixed.py
grepctl/scripts/ingest_video_files.py
grepctl/scripts/show_status.py
grepctl/search/__init__.py
grepctl/search/vector_search.py
grepctl/utils/__init__.py
grepctl-0.3.2.dist-info/licenses/LICENSE
grepctl-0.3.2.dist-info/METADATA
grepctl-0.3.2.dist-info/WHEEL
grepctl-0.3.2.dist-info/entry_points.txt
grepctl-0.3.2.dist-info/top_level.txt
grepctl-0.3.2.dist-info/RECORD
